raypyc/__init__.py
raypyc/__init__.pyi
raypyc/config_api.json
raypyc/raygui_api.json
raypyc/raylib_api.json
raypyc/raymath_api.json
raypyc/reasings.py
raypyc/rlgl_api.json
raypyc/colors/__init__.py
raypyc/colors/__init__.pyi
raypyc/defines/__init__.py
raypyc/defines/__init__.pyi
raypyc/enums/__init__.py
raypyc/enums/__init__.pyi
raypyc/libs/libraylib.so
raypyc/libs/raylib.dll
raypyc/libs/raypyc_extra_functions.dll
raypyc/libs/raypyc_extra_functions.so
raypyc/libs/wasmraylib.so
raypyc/structures/__init__.py
raypyc/structures/__init__.pyi
raypyc-0.1.8.dist-info/LICENSE
raypyc-0.1.8.dist-info/METADATA
raypyc-0.1.8.dist-info/WHEEL
raypyc-0.1.8.dist-info/top_level.txt
raypyc-0.1.8.dist-info/RECORD
