Metadata-Version: 2.1
Name: raypyc
Version: 0.1.8
Summary: A python wrapper for raylib using ctypes
Home-page: https://github.com/sDos280/raylib-python-ctypes
Author: Dor Shapira
Author-email: sdor2803@gmail.com
License: MIT License
Classifier: Programming Language :: Python :: 3
Classifier: License :: OSI Approved :: MIT License
License-File: LICENSE
Requires-Dist: setuptools (>=42)
Requires-Dist: wheel
